LICENSE
README.md
pg_rls/__init__.py
pg_rls/alembic/__init__.py
pg_rls/alembic/comparator.py
pg_rls/alembic/operations/__init__.py
pg_rls/alembic/operations/policy.py
pg_rls/alembic/operations/policy_sql.py
pg_rls/alembic/operations/rls.py
pg_rls/policy.py
pg_rls/sqlalchemy.py
pg_rls_sqlalchemy-0.1.2.dist-info/LICENSE
pg_rls_sqlalchemy-0.1.2.dist-info/METADATA
pg_rls_sqlalchemy-0.1.2.dist-info/WHEEL
pg_rls_sqlalchemy-0.1.2.dist-info/RECORD
