Metadata-Version: 2.1
Name: pg-rls-sqlalchemy
Version: 0.1.2
Summary: 
Author: Matthew Beatty
Author-email: beattyml1@gmail.com
Requires-Python: >=3.11,<4.0
Classifier: Programming Language :: Python :: 3
Classifier: Programming Language :: Python :: 3.11
Classifier: Programming Language :: Python :: 3.12
Requires-Dist: alembic (>=1.13.2,<2.0.0)
Requires-Dist: sqlalchemy (>=2.0.32,<3.0.0)
